yapi_mcp/__init__.py
yapi_mcp/__main__.py
yapi_mcp/config.py
yapi_mcp/server.py
yapi_mcp/tools/__init__.py
yapi_mcp/yapi/__init__.py
yapi_mcp/yapi/client.py
yapi_mcp/yapi/errors.py
yapi_mcp/yapi/models.py
yapi_mcp-0.1.3.dist-info/METADATA
yapi_mcp-0.1.3.dist-info/WHEEL
yapi_mcp-0.1.3.dist-info/entry_points.txt
yapi_mcp-0.1.3.dist-info/licenses/LICENSE
yapi_mcp-0.1.3.dist-info/RECORD
