Metadata-Version: 2.4
Name: yapi-mcp
Version: 0.1.3
Summary: Model Context Protocol server for YApi 1.12.0 API management platform
Project-URL: Homepage, https://github.com/geq1fan/yapi-mcp
Project-URL: Repository, https://github.com/geq1fan/yapi-mcp
Project-URL: Issues, https://github.com/geq1fan/yapi-mcp/issues
Author: YApi MCP Team
License: MIT
License-File: LICENSE
Keywords: api,fastmcp,mcp,model-context-protocol,yapi
Classifier: Development Status :: 4 - Beta
Classifier: Intended Audience :: Developers
Classifier: License :: OSI Approved :: MIT License
Classifier: Programming Language :: Python :: 3
Classifier: Programming Language :: Python :: 3.11
Classifier: Programming Language :: Python :: 3.12
Classifier: Programming Language :: Python :: 3.13
Classifier: Topic :: Software Development :: Libraries :: Python Modules
Requires-Python: >=3.11
Requires-Dist: fastmcp>=2.0.0
Requires-Dist: httpx>=0.27.0
Requires-Dist: markdown>=3.5.0
Requires-Dist: pydantic-settings>=2.0.0
Provides-Extra: dev
Requires-Dist: pytest-asyncio>=0.23.0; extra == 'dev'
Requires-Dist: pytest>=8.0.0; extra == 'dev'
Requires-Dist: respx>=0.21.0; extra == 'dev'
Requires-Dist: ruff>=0.4.0; extra == 'dev'
